HexMeshCylinders/__init__.py
HexMeshCylinders/boundary.py
HexMeshCylinders/boundary_editor.py
HexMeshCylinders/boundary_list.py
HexMeshCylinders/cell.py
HexMeshCylinders/cell_list.py
HexMeshCylinders/cylinder.py
HexMeshCylinders/face.py
HexMeshCylinders/face_list.py
HexMeshCylinders/headers.py
HexMeshCylinders/internal_face_list.py
HexMeshCylinders/point.py
HexMeshCylinders/point_list.py
HexMeshCylinders/printer.py
HexMeshCylinders/stack.py
HexMeshCylinders/Shapes/__init__.py
HexMeshCylinders/Shapes/circle.py
HexMeshCylinders/Shapes/ellipse.py
HexMeshCylinders/Shapes/rectangle.py
HexMeshCylinders/Shapes/shape2D.py
HexMeshCylinders-0.0.3.dist-info/LICENSE
HexMeshCylinders-0.0.3.dist-info/METADATA
HexMeshCylinders-0.0.3.dist-info/WHEEL
HexMeshCylinders-0.0.3.dist-info/top_level.txt
HexMeshCylinders-0.0.3.dist-info/RECORD
