Metadata-Version: 2.1
Name: HexMeshCylinders
Version: 0.0.3
Summary: Creates structured hexahedral meshes for OpenFOAM
Home-page: https://github.com/gui-miotto/HexMeshCylinders
Author: Gui Miotto
Author-email: guilherme.miotto@gmail.com
License: UNKNOWN
Platform: UNKNOWN
Classifier: Programming Language :: Python :: 3
Classifier: License :: OSI Approved :: MIT License
Classifier: Operating System :: OS Independent
Requires-Python: >=3.6
Requires-Dist: numpy
